{
  "1342149599648813148": {
    "steamId": "76561198184088418",
    "name": "mikey",
    "rank": "☆・parallax",
    "verifiedAt": "2025-06-22T00:03:07.470Z"
  },
  "193909360219389952": {
    "steamId": "76561198124391666",
    "name": "Nick",
    "rank": "☆・void",
    "verifiedAt": "2025-06-22T00:56:22.926Z"
  },
  "509017386868015136": {
    "steamId": "76561198879625644",
    "name": "Mox",
    "rank": "☆・astral",
    "verifiedAt": "2025-06-22T00:04:00.605Z"
  },
  "1261882298005983292": {
    "steamId": "76561199125953480",
    "name": "waffle",
    "rank": "☆・stellar",
    "verifiedAt": "2025-06-22T00:45:55.675Z"
  },
  "1052344418025361468": {
    "steamId": "76561198932943367",
    "name": "sosa!",
    "rank": "☆・stellar",
    "verifiedAt": "2025-06-22T00:55:18.029Z"
  },
  "463475362521939978": {
    "steamId": "76561198170402266",
    "name": "Sad",
    "rank": "☆・eclipse",
    "verifiedAt": "2025-06-22T02:39:09.418Z"
  },
  "659373053892886530": {
    "steamId": "76561199013190213",
    "name": "TinyMix",
    "rank": "☆・stellar",
    "verifiedAt": "2025-06-22T05:27:20.287Z"
  },
  "1282548673733202003": {
    "steamId": "76561198085210353",
    "name": "GarryfromGmod",
    "rank": "☆・stellar",
    "verifiedAt": "2025-06-22T05:45:36.391Z"
  },
  "746032909500153959": {
    "steamId": "76561198302385404",
    "name": "Baby Sid",
    "rank": "☆・eclipse",
    "verifiedAt": "2025-06-22T05:56:18.363Z"
  },
  "1037201848001646703": {
    "steamId": "76561199028394970",
    "name": "fent ryder",
    "rank": "☆・stellar",
    "verifiedAt": "2025-06-22T06:10:39.830Z"
  },
  "464384696000839681": {
    "steamId": "76561198067637706",
    "name": "zoe7",
    "rank": "☆・parallax",
    "verifiedAt": "2025-06-22T06:47:17.207Z"
  }
}